ultralytics/__init__.py
ultralytics/cfg/__init__.py
ultralytics/data/__init__.py
ultralytics/data/annotator.py
ultralytics/data/augment.py
ultralytics/data/base.py
ultralytics/data/build.py
ultralytics/data/converter.py
ultralytics/data/dataset.py
ultralytics/data/loaders.py
ultralytics/data/split_dota.py
ultralytics/data/utils.py
ultralytics/engine/__init__.py
ultralytics/engine/exporter.py
ultralytics/engine/model.py
ultralytics/engine/predictor.py
ultralytics/engine/results.py
ultralytics/engine/trainer.py
ultralytics/engine/tuner.py
ultralytics/engine/validator.py
ultralytics/hub/__init__.py
ultralytics/hub/auth.py
ultralytics/hub/session.py
ultralytics/hub/utils.py
ultralytics/hub/google/__init__.py
ultralytics/models/__init__.py
ultralytics/models/fastsam/__init__.py
ultralytics/models/fastsam/model.py
ultralytics/models/fastsam/predict.py
ultralytics/models/fastsam/utils.py
ultralytics/models/fastsam/val.py
ultralytics/models/nas/__init__.py
ultralytics/models/nas/model.py
ultralytics/models/nas/predict.py
ultralytics/models/nas/val.py
ultralytics/models/rtdetr/__init__.py
ultralytics/models/rtdetr/model.py
ultralytics/models/rtdetr/predict.py
ultralytics/models/rtdetr/train.py
ultralytics/models/rtdetr/val.py
ultralytics/models/sam/__init__.py
ultralytics/models/sam/amg.py
ultralytics/models/sam/build.py
ultralytics/models/sam/model.py
ultralytics/models/sam/predict.py
ultralytics/models/sam/modules/__init__.py
ultralytics/models/sam/modules/blocks.py
ultralytics/models/sam/modules/decoders.py
ultralytics/models/sam/modules/encoders.py
ultralytics/models/sam/modules/memory_attention.py
ultralytics/models/sam/modules/sam.py
ultralytics/models/sam/modules/tiny_encoder.py
ultralytics/models/sam/modules/transformer.py
ultralytics/models/sam/modules/utils.py
ultralytics/models/utils/__init__.py
ultralytics/models/utils/loss.py
ultralytics/models/utils/ops.py
ultralytics/models/yolo/__init__.py
ultralytics/models/yolo/model.py
htl_viguard-0.1.0.dist-info/LICENSE
htl_viguard-0.1.0.dist-info/METADATA
htl_viguard-0.1.0.dist-info/WHEEL
htl_viguard-0.1.0.dist-info/top_level.txt
htl_viguard-0.1.0.dist-info/RECORD
