Metadata-Version: 2.2
Name: htl-viguard
Version: 0.1.0
Summary: DATN ViGuard - Ultralytics
Home-page: https://github.com/yourusername/my_package
Author: Hoang Thanh Lam
Author-email: lamkt547749@gmail.com
Classifier: Programming Language :: Python :: 3
Classifier: License :: OSI Approved :: MIT License
Classifier: Operating System :: OS Independent
Requires-Python: >=3.7
License-File: LICENSE
Dynamic: author
Dynamic: author-email
Dynamic: classifier
Dynamic: description-content-type
Dynamic: home-page
Dynamic: requires-python
Dynamic: summary
